{
  "annotations": {
    "list": [
      {
        "builtIn": 1,
        "datasource": {"type": "grafana", "uid": "-- Grafana --"},
        "enable": true,
        "hide": true,
        "iconColor": "rgba(0, 211, 255, 1)",
        "name": "Annotations & Alerts",
        "type": "dashboard"
      }
    ]
  },
  "description": "OEE (Availability × Performance × Quality), MTBF estimate, micro-stoppages, per-machine KPI comparison.",
  "editable": true,
  "fiscalYearStartMonth": 0,
  "graphTooltip": 1,
  "id": null,
  "links": [],
  "panels": [
    {
      "datasource": {"type": "prometheus", "uid": "prometheus"},
      "fieldConfig": {
        "defaults": {
          "color": {"mode": "thresholds"},
          "decimals": 1,
          "mappings": [],
          "max": 100,
          "min": 0,
          "thresholds": {
            "mode": "absolute",
            "steps": [
              {"color": "red", "value": null},
              {"color": "yellow", "value": 65},
              {"color": "green", "value": 85}
            ]
          },
          "unit": "percent"
        },
        "overrides": []
      },
      "gridPos": {"h": 8, "w": 6, "x": 0, "y": 0},
      "id": 1,
      "options": {
        "minVizHeight": 75,
        "minVizWidth": 75,
        "orientation": "auto",
        "reduceOptions": {"calcs": ["lastNotNull"], "fields": "", "values": false},
        "showThresholdLabels": true,
        "showThresholdMarkers": true
      },
      "targets": [
        {
          "datasource": {"type": "prometheus", "uid": "prometheus"},
          "expr": "avg_over_time(production_run{machine_id=~\"$machine_id\"}[8h]) * clamp_max(900.0 / clamp_min(avg_over_time(last_cycle_time_ms{machine_id=~\"$machine_id\"}[8h]), 1), 1) * (rate(ok_counter_total{machine_id=~\"$machine_id\"}[8h]) / clamp_min(rate(ok_counter_total{machine_id=~\"$machine_id\"}[8h]) + rate(nok_counter_total{machine_id=~\"$machine_id\"}[8h]), 0.001)) * 100",
          "legendFormat": "{{machine_id}}",
          "refId": "A"
        }
      ],
      "title": "OEE % (8h estimate)",
      "type": "gauge"
    },
    {
      "datasource": {"type": "prometheus", "uid": "prometheus"},
      "fieldConfig": {
        "defaults": {
          "color": {"mode": "thresholds"},
          "decimals": 1,
          "mappings": [],
          "max": 100,
          "min": 0,
          "thresholds": {
            "mode": "absolute",
            "steps": [
              {"color": "red", "value": null},
              {"color": "yellow", "value": 80},
              {"color": "green", "value": 90}
            ]
          },
          "unit": "percent"
        },
        "overrides": []
      },
      "gridPos": {"h": 4, "w": 6, "x": 6, "y": 0},
      "id": 2,
      "options": {
        "colorMode": "value",
        "graphMode": "area",
        "justifyMode": "center",
        "orientation": "auto",
        "reduceOptions": {"calcs": ["lastNotNull"], "fields": "", "values": false},
        "textMode": "auto"
      },
      "targets": [
        {
          "datasource": {"type": "prometheus", "uid": "prometheus"},
          "expr": "avg_over_time(production_run{machine_id=~\"$machine_id\"}[8h]) * 100",
          "legendFormat": "{{machine_id}}",
          "refId": "A"
        }
      ],
      "title": "Availability % (8h)",
      "type": "stat"
    },
    {
      "datasource": {"type": "prometheus", "uid": "prometheus"},
      "fieldConfig": {
        "defaults": {
          "color": {"mode": "thresholds"},
          "decimals": 1,
          "mappings": [],
          "max": 100,
          "min": 0,
          "thresholds": {
            "mode": "absolute",
            "steps": [
              {"color": "red", "value": null},
              {"color": "yellow", "value": 75},
              {"color": "green", "value": 90}
            ]
          },
          "unit": "percent"
        },
        "overrides": []
      },
      "gridPos": {"h": 4, "w": 6, "x": 12, "y": 0},
      "id": 3,
      "options": {
        "colorMode": "value",
        "graphMode": "area",
        "justifyMode": "center",
        "orientation": "auto",
        "reduceOptions": {"calcs": ["lastNotNull"], "fields": "", "values": false},
        "textMode": "auto"
      },
      "targets": [
        {
          "datasource": {"type": "prometheus", "uid": "prometheus"},
          "expr": "clamp_max(900.0 / clamp_min(avg_over_time(last_cycle_time_ms{machine_id=~\"$machine_id\"}[5m]), 1), 100) * 100",
          "legendFormat": "{{machine_id}}",
          "refId": "A"
        }
      ],
      "title": "Performance % (ideal 900ms baseline)",
      "type": "stat"
    },
    {
      "datasource": {"type": "prometheus", "uid": "prometheus"},
      "fieldConfig": {
        "defaults": {
          "color": {"mode": "thresholds"},
          "decimals": 2,
          "mappings": [],
          "max": 100,
          "min": 0,
          "thresholds": {
            "mode": "absolute",
            "steps": [
              {"color": "red", "value": null},
              {"color": "yellow", "value": 95},
              {"color": "green", "value": 98}
            ]
          },
          "unit": "percent"
        },
        "overrides": []
      },
      "gridPos": {"h": 4, "w": 6, "x": 18, "y": 0},
      "id": 4,
      "options": {
        "colorMode": "value",
        "graphMode": "area",
        "justifyMode": "center",
        "orientation": "auto",
        "reduceOptions": {"calcs": ["lastNotNull"], "fields": "", "values": false},
        "textMode": "auto"
      },
      "targets": [
        {
          "datasource": {"type": "prometheus", "uid": "prometheus"},
          "expr": "rate(ok_counter_total{machine_id=~\"$machine_id\"}[5m]) / clamp_min(rate(ok_counter_total{machine_id=~\"$machine_id\"}[5m]) + rate(nok_counter_total{machine_id=~\"$machine_id\"}[5m]), 0.001) * 100",
          "legendFormat": "{{machine_id}}",
          "refId": "A"
        }
      ],
      "title": "Quality % (5m)",
      "type": "stat"
    },
    {
      "datasource": {"type": "prometheus", "uid": "prometheus"},
      "fieldConfig": {
        "defaults": {
          "color": {"mode": "thresholds"},
          "decimals": 2,
          "mappings": [],
          "thresholds": {
            "mode": "absolute",
            "steps": [
              {"color": "red", "value": null},
              {"color": "yellow", "value": 0.5},
              {"color": "green", "value": 1}
            ]
          },
          "unit": "h"
        },
        "overrides": []
      },
      "gridPos": {"h": 4, "w": 6, "x": 6, "y": 4},
      "id": 5,
      "options": {
        "colorMode": "value",
        "graphMode": "none",
        "justifyMode": "center",
        "orientation": "auto",
        "reduceOptions": {"calcs": ["lastNotNull"], "fields": "", "values": false},
        "textMode": "auto"
      },
      "targets": [
        {
          "datasource": {"type": "prometheus", "uid": "prometheus"},
          "expr": "avg_over_time(production_run{machine_id=~\"$machine_id\"}[8h]) * 8 / clamp_min(changes(production_run{machine_id=~\"$machine_id\"}[8h]) / 2, 1)",
          "legendFormat": "{{machine_id}}",
          "refId": "A"
        }
      ],
      "title": "MTBF Estimate (8h, hours)",
      "type": "stat"
    },
    {
      "datasource": {"type": "prometheus", "uid": "prometheus"},
      "fieldConfig": {
        "defaults": {
          "color": {"mode": "thresholds"},
          "mappings": [],
          "thresholds": {
            "mode": "absolute",
            "steps": [
              {"color": "green", "value": null},
              {"color": "yellow", "value": 5},
              {"color": "red", "value": 15}
            ]
          },
          "unit": "short"
        },
        "overrides": []
      },
      "gridPos": {"h": 4, "w": 6, "x": 12, "y": 4},
      "id": 6,
      "options": {
        "colorMode": "background",
        "graphMode": "area",
        "justifyMode": "center",
        "orientation": "auto",
        "reduceOptions": {"calcs": ["lastNotNull"], "fields": "", "values": false},
        "textMode": "auto"
      },
      "targets": [
        {
          "datasource": {"type": "prometheus", "uid": "prometheus"},
          "expr": "changes(production_run{machine_id=~\"$machine_id\"}[1h]) / 2",
          "legendFormat": "{{machine_id}}",
          "refId": "A"
        }
      ],
      "title": "Stop Events (last 1h)",
      "type": "stat"
    },
    {
      "datasource": {"type": "prometheus", "uid": "prometheus"},
      "fieldConfig": {
        "defaults": {
          "color": {"mode": "thresholds"},
          "mappings": [],
          "thresholds": {
            "mode": "absolute",
            "steps": [
              {"color": "green", "value": null},
              {"color": "yellow", "value": 10},
              {"color": "red", "value": 30}
            ]
          },
          "unit": "short"
        },
        "overrides": []
      },
      "gridPos": {"h": 4, "w": 6, "x": 18, "y": 4},
      "id": 7,
      "options": {
        "colorMode": "background",
        "graphMode": "area",
        "justifyMode": "center",
        "orientation": "auto",
        "reduceOptions": {"calcs": ["lastNotNull"], "fields": "", "values": false},
        "textMode": "auto"
      },
      "targets": [
        {
          "datasource": {"type": "prometheus", "uid": "prometheus"},
          "expr": "count_over_time((last_stoppage_time_ms{machine_id=~\"$machine_id\"} > 0 and last_stoppage_time_ms{machine_id=~\"$machine_id\"} < 30000)[1h:15s])",
          "legendFormat": "{{machine_id}}",
          "refId": "A"
        }
      ],
      "title": "Micro-Stoppages < 30s (last 1h)",
      "type": "stat"
    },
    {
      "datasource": {"type": "prometheus", "uid": "prometheus"},
      "fieldConfig": {
        "defaults": {
          "color": {"mode": "palette-classic"},
          "custom": {
            "axisBorderShow": false,
            "axisCenteredZero": false,
            "axisColorMode": "text",
            "axisLabel": "OEE %",
            "axisPlacement": "auto",
            "fillOpacity": 80,
            "gradientMode": "none",
            "hideFrom": {"legend": false, "tooltip": false, "viz": false},
            "lineWidth": 1,
            "scaleDistribution": {"type": "linear"},
            "thresholdsStyle": {"mode": "off"}
          },
          "decimals": 1,
          "mappings": [],
          "max": 100,
          "min": 0,
          "thresholds": {
            "mode": "absolute",
            "steps": [
              {"color": "red", "value": null},
              {"color": "yellow", "value": 65},
              {"color": "green", "value": 85}
            ]
          },
          "unit": "percent"
        },
        "overrides": []
      },
      "gridPos": {"h": 8, "w": 24, "x": 0, "y": 8},
      "id": 8,
      "options": {
        "barRadius": 0.05,
        "barWidth": 0.6,
        "fullHighlight": false,
        "groupWidth": 0.7,
        "legend": {"displayMode": "list", "placement": "bottom", "showLegend": true},
        "orientation": "horizontal",
        "showValue": "auto",
        "stacking": "none",
        "tooltip": {"mode": "multi", "sort": "none"},
        "xTickLabelRotation": 0,
        "xTickLabelSpacing": 200
      },
      "targets": [
        {
          "datasource": {"type": "prometheus", "uid": "prometheus"},
          "expr": "avg_over_time(production_run{machine_id=~\"$machine_id\"}[8h]) * clamp_max(900.0 / clamp_min(avg_over_time(last_cycle_time_ms{machine_id=~\"$machine_id\"}[8h]), 1), 1) * (rate(ok_counter_total{machine_id=~\"$machine_id\"}[8h]) / clamp_min(rate(ok_counter_total{machine_id=~\"$machine_id\"}[8h]) + rate(nok_counter_total{machine_id=~\"$machine_id\"}[8h]), 0.001)) * 100",
          "legendFormat": "{{machine_id}}",
          "refId": "A"
        }
      ],
      "title": "OEE Comparison by Machine",
      "transformations": [],
      "type": "barchart"
    },
    {
      "datasource": {"type": "prometheus", "uid": "prometheus"},
      "fieldConfig": {
        "defaults": {
          "color": {"mode": "palette-classic"},
          "custom": {
            "axisBorderShow": false,
            "axisCenteredZero": false,
            "axisColorMode": "text",
            "axisLabel": "%",
            "axisPlacement": "auto",
            "barAlignment": 0,
            "drawStyle": "line",
            "fillOpacity": 10,
            "gradientMode": "none",
            "hideFrom": {"legend": false, "tooltip": false, "viz": false},
            "insertNulls": false,
            "lineInterpolation": "smooth",
            "lineWidth": 2,
            "pointSize": 5,
            "scaleDistribution": {"type": "linear"},
            "showPoints": "never",
            "spanNulls": false,
            "stacking": {"group": "A", "mode": "none"},
            "thresholdsStyle": {"mode": "line"}
          },
          "decimals": 1,
          "mappings": [],
          "max": 100,
          "min": 0,
          "thresholds": {
            "mode": "absolute",
            "steps": [
              {"color": "transparent", "value": null},
              {"color": "red", "value": 65},
              {"color": "yellow", "value": 85}
            ]
          },
          "unit": "percent"
        },
        "overrides": []
      },
      "gridPos": {"h": 8, "w": 24, "x": 0, "y": 16},
      "id": 9,
      "options": {
        "legend": {"calcs": ["mean", "min"], "displayMode": "table", "placement": "right", "showLegend": true},
        "tooltip": {"mode": "multi", "sort": "none"}
      },
      "targets": [
        {
          "datasource": {"type": "prometheus", "uid": "prometheus"},
          "expr": "avg_over_time(production_run{machine_id=~\"$machine_id\"}[5m]) * 100",
          "legendFormat": "{{machine_id}} – availability",
          "refId": "A"
        }
      ],
      "title": "Availability Trend (5m rolling)",
      "type": "timeseries"
    }
  ],
  "refresh": "5s",
  "schemaVersion": 39,
  "tags": ["factory", "oee", "kpi"],
  "templating": {
    "list": [
      {
        "current": {"selected": true, "text": "All", "value": "$__all"},
        "datasource": {"type": "prometheus", "uid": "prometheus"},
        "definition": "label_values(machine_on, machine_id)",
        "hide": 0,
        "includeAll": true,
        "multi": false,
        "name": "machine_id",
        "options": [],
        "query": {
          "query": "label_values(machine_on, machine_id)",
          "refId": "StandardVariableQuery"
        },
        "refresh": 2,
        "regex": "",
        "sort": 1,
        "type": "query",
        "label": "Machine"
      }
    ]
  },
  "time": {"from": "now-1h", "to": "now"},
  "timepicker": {},
  "timezone": "browser",
  "title": "03 – OEE & KPI",
  "uid": "oee-kpi-03",
  "version": 1,
  "weekStart": ""
}
